LICENSE
MANIFEST.in
README.md
requirements.txt
setup.py
pytest_testdata/__init__.py
pytest_testdata/plugin.py
pytest_testdata.egg-info/PKG-INFO
pytest_testdata.egg-info/SOURCES.txt
pytest_testdata.egg-info/dependency_links.txt
pytest_testdata.egg-info/entry_points.txt
pytest_testdata.egg-info/requires.txt
pytest_testdata.egg-info/top_level.txt
pytest_testdata.egg-info/zip-safe
tests/test_pytest_relative_path.py