Metadata-Version: 2.1
Name: pytest-testdata
Version: 0.1.1
Summary: Get and load testdata in pytest projects
Home-page: https://github.com/hanzhichao/pytest-testdata
Author: Han Zhichao
Author-email: superhin@126.com
License: MIT license
Keywords: pytest,py.test,relative path,datetime format path
Classifier: Framework :: Pytest
Classifier: Programming Language :: Python
Classifier: Topic :: Software Development :: Testing
Classifier: Programming Language :: Python :: 3.7
License-File: LICENSE
Requires-Dist: pytest
Requires-Dist: pytest-runner
Requires-Dist: filez
